docs/conf.py
docs/poly.py
docs/preprocess.py
sample/templates/icpc_domestic/postprocess.py
sample/templates/icpc_domestic/preprocess.py
statements_manager/__init__.py
statements_manager/main.py
statements_manager/template.py
statements_manager/src/__init__.py
statements_manager/src/convert_task_runner.py
statements_manager/src/execute_config.py
statements_manager/src/output_file_kind.py
statements_manager/src/project.py
statements_manager/src/render_result_cache.py
statements_manager/src/renderer.py
statements_manager/src/setup_problem.py
statements_manager/src/statement_location_mode.py
statements_manager/src/utils.py
statements_manager/src/variables_converter.py
statements_manager/src/auth/login_status.py
statements_manager/src/auth/oauth_config.py
statements_manager/src/auth/oauth_login.py
statements_manager/src/auth/oauth_login_ci.py
statements_manager/src/auth/oauth_login_reg_creds.py
statements_manager/src/auth/oauth_routing.py
statements_manager/src/params_maker/__init__.py
statements_manager/src/params_maker/lang_to_class.py
statements_manager/src/params_maker/params_maker.py
statements_manager/src/params_maker/languages/__init__.py
statements_manager/src/params_maker/languages/cplusplus.py
statements_manager-2.0.2.dist-info/licenses/LICENSE
tests/test_auth_priority.py
tests/test_e2e.py
tests/test_fail_on_suggestions.py
tests/test_setup_problem.py
tests/test_utils.py
tests/test_variables_converter.py
statements_manager-2.0.2.dist-info/METADATA
statements_manager-2.0.2.dist-info/WHEEL
statements_manager-2.0.2.dist-info/entry_points.txt
statements_manager-2.0.2.dist-info/top_level.txt
statements_manager-2.0.2.dist-info/RECORD
