Metadata-Version: 2.4
Name: statements-manager
Version: 2.0.2
Summary: 競技プログラミングの作問時に使用する、問題文管理を便利にするツール
Author-email: Yuya Sugie <y.sugie.15739d@gmail.com>
Classifier: Development Status :: 4 - Beta
Classifier: Environment :: Console
Classifier: Intended Audience :: Developers
Classifier: Operating System :: OS Independent
Classifier: Programming Language :: Python :: 3.9
Classifier: Topic :: Internet :: WWW/HTTP
Classifier: Topic :: Software Development
Classifier: Topic :: Utilities
Requires-Python: >=3.9.12
License-File: LICENSE
Requires-Dist: google-api-python-client
Requires-Dist: google-auth-httplib2
Requires-Dist: google-auth-oauthlib
Requires-Dist: markdown>=3.3.1
Requires-Dist: jinja2
Requires-Dist: toml
Requires-Dist: colorlog
Requires-Dist: pdfkit>=1.0.0
Requires-Dist: pymdown-extensions
Requires-Dist: pyquery>=1.2.4
Requires-Dist: rich
Provides-Extra: dev
Requires-Dist: flake8; extra == "dev"
Requires-Dist: isort; extra == "dev"
Requires-Dist: black; extra == "dev"
Requires-Dist: mypy; extra == "dev"
Requires-Dist: pytest; extra == "dev"
Provides-Extra: dynamic
Dynamic: license-file
